jackdaw/__init__.py
jackdaw/__main__.py
jackdaw/_version.py
jackdaw/aclpwn.py
jackdaw/cypher_test.py
jackdaw/pwreportgen.py
jackdaw/common/__init__.py
jackdaw/common/apq.py
jackdaw/common/cpucount.py
jackdaw/common/ldap.py
jackdaw/common/proxy.py
jackdaw/credentials/__init__.py
jackdaw/credentials/credentials.py
jackdaw/dbmodel/__init__.py
jackdaw/dbmodel/adallowedtoact.py
jackdaw/dbmodel/adcomp.py
jackdaw/dbmodel/adgplink.py
jackdaw/dbmodel/adgpo.py
jackdaw/dbmodel/adgroup.py
jackdaw/dbmodel/adinfo.py
jackdaw/dbmodel/adobjprops.py
jackdaw/dbmodel/adou.py
jackdaw/dbmodel/adschemaentry.py
jackdaw/dbmodel/adsd.py
jackdaw/dbmodel/adspn.py
jackdaw/dbmodel/adtrust.py
jackdaw/dbmodel/aduser.py
jackdaw/dbmodel/constrained.py
jackdaw/dbmodel/credential.py
jackdaw/dbmodel/customcred.py
jackdaw/dbmodel/customtarget.py
jackdaw/dbmodel/dnslookup.py
jackdaw/dbmodel/edge.py
jackdaw/dbmodel/edgelookup.py
jackdaw/dbmodel/graphinfo.py
jackdaw/dbmodel/hashentry.py
jackdaw/dbmodel/kerberoast.py
jackdaw/dbmodel/kerberostickets.py
jackdaw/dbmodel/localgroup.py
jackdaw/dbmodel/lsasecrets.py
jackdaw/dbmodel/netdacl.py
jackdaw/dbmodel/netdir.py
jackdaw/dbmodel/neterror.py
jackdaw/dbmodel/netfile.py
jackdaw/dbmodel/netsession.py
jackdaw/dbmodel/netshare.py
jackdaw/dbmodel/portaluser.py
jackdaw/dbmodel/rdnslookup.py
jackdaw/dbmodel/regsession.py
jackdaw/dbmodel/smbfile.py
jackdaw/dbmodel/smbfinger.py
jackdaw/dbmodel/smbinterface.py
jackdaw/dbmodel/smbprotocols.py
jackdaw/dbmodel/smbvuln.py
jackdaw/dbmodel/spnservice.py
jackdaw/dbmodel/utils/__init__.py
jackdaw/dbmodel/utils/addacl.py
jackdaw/dbmodel/utils/pagination.py
jackdaw/dbmodel/utils/serializer.py
jackdaw/dbmodel/utils/tokengroup.py
jackdaw/dbmodel/utils/uacflags.py
jackdaw/external/__init__.py
jackdaw/external/aiocmd/__init__.py
jackdaw/external/aiocmd/setup.py
jackdaw/external/aiocmd/aiocmd/__init__.py
jackdaw/external/aiocmd/aiocmd/aiocmd.py
jackdaw/external/aiocmd/aiocmd/nested_completer.py
jackdaw/gatherer/__init__.py
jackdaw-0.4.1.dist-info/METADATA
jackdaw-0.4.1.dist-info/WHEEL
jackdaw-0.4.1.dist-info/entry_points.txt
jackdaw-0.4.1.dist-info/top_level.txt
jackdaw-0.4.1.dist-info/RECORD
